{
  "Treatments": [
    {
      "id": "5",
      "treatment": "Nuero"
    },
    {
      "id": "1",
      "treatment": "Medication Therapy"
    },
    {
      "id": "2",
      "treatment": "Surgical Treatments"
    },
    {
      "id": "3",
      "treatment": "Radiation Therapy"
    },
    {
      "id": "4",
      "treatment": "Cognitive Behavioral Therapy (CBT)"
    },
    {
      "id": "6",
      "treatment": "Psychoanalysis"
    },
    {
      "id": "7",
      "treatment": "Mindfulness-Based Stress Reduction (MBSR)"
    },
    {
      "id": "8",
      "treatment": "Dietary Adjustments"
    },
    {
      "id": "9",
      "treatment": "Nutritional Supplements"
    },
    {
      "id": "10",
      "treatment": "Hormone Replacement Therapy (HRT)"
    },
    {
      "id": "3",
      "treatment": "hh"
    }
  ]
}